{"cameraMode":{"drawMode":0,"name":"Shaded","section":"Shading Mode"},"sceneLighting":false,"audioPlay":false,"sceneViewState":{"m_AlwaysRefresh":false,"showFog":true,"showSkybox":false,"showFlares":true,"showImageEffects":true,"showParticleSystems":true,"showVisualEffectGraphs":true,"m_FxEnabled":true},"in2DMode":false,"pivot":{"x":-6.853403568267822,"y":7.160972595214844,"z":3.8441503047943117},"rotation":{"x":-0.019217336550354959,"y":-0.9813820719718933,"z":0.14045003056526185,"w":-0.1309671849012375},"size":1.069379210472107,"orthographic":false}