{"cameraMode":{"drawMode":0,"name":"Shaded","section":"Shading Mode"},"sceneLighting":false,"audioPlay":false,"sceneViewState":{"m_AlwaysRefresh":false,"showFog":true,"showSkybox":false,"showFlares":true,"showImageEffects":true,"showParticleSystems":true,"showVisualEffectGraphs":true,"m_FxEnabled":true},"in2DMode":false,"pivot":{"x":-40.765743255615237,"y":-65.33918762207031,"z":-100.14414978027344},"rotation":{"x":-0.012420178391039372,"y":-0.8921400308609009,"z":-0.023965736851096154,"w":0.4514296054840088},"size":5.223324298858643,"orthographic":false}